utiles-0.8.0.dist-info/METADATA
utiles-0.8.0.dist-info/WHEEL
utiles-0.8.0.dist-info/entry_points.txt
utiles/__about__.py
utiles/__init__.py
utiles/__main__.py
utiles/_click.py
utiles/_legacy/__init__.py
utiles/_legacy/cli.py
utiles/_utiles.cpython-314t-x86_64-linux-gnu.so
utiles/_utiles.pyi
utiles/cli.py
utiles/dev/__init__.py
utiles/dev/testing.py
utiles/py.typed
utiles/rio_plugin.py
utiles-0.8.0.dist-info/RECORD
