Metadata-Version: 2.4
Name: utiles
Version: 0.8.0
Classifier: Intended Audience :: Developers
Classifier: License :: OSI Approved :: Apache Software License
Classifier: License :: OSI Approved :: MIT License
Classifier: Programming Language :: Python :: 3 :: Only
Classifier: Programming Language :: Python :: 3
Classifier: Programming Language :: Python :: 3.11
Classifier: Programming Language :: Python :: 3.12
Classifier: Programming Language :: Python :: 3.13
Classifier: Programming Language :: Python :: 3.14
Classifier: Programming Language :: Python :: Implementation :: CPython
Classifier: Programming Language :: Python :: Implementation :: PyPy
Classifier: Programming Language :: Python
Classifier: Programming Language :: Rust
Classifier: Typing :: Typed
Summary: utiles = (utils + tiles) * rust
Home-Page: https://github.com/jessekrubin/utiles
Author-email: jesse rubin <jessekrubin@gmail.com>
Maintainer-email: jesse rubin <jessekrubin@gmail.com>
Requires-Python: >=3.11
Project-URL: Changelog, https://github.com/jessekrubin/utiles/blob/main/CHANGELOG.md
Project-URL: Documentation, https://github.com/jessekrubin/utiles/blob/main/utiles-pyo3/README.md
Project-URL: Homepage, https://github.com/jessekrubin/utiles
Project-URL: Repository, https://github.com/jessekrubin/utiles
